flask_threads-0.2.0.dist-info/licenses/LICENSE
flaskthreads/__init__.py
flaskthreads/thread_helpers.py
flask_threads-0.2.0.dist-info/METADATA
flask_threads-0.2.0.dist-info/WHEEL
flask_threads-0.2.0.dist-info/top_level.txt
flask_threads-0.2.0.dist-info/RECORD
