Metadata-Version: 2.4
Name: Flask-Threads
Version: 0.2.0
Summary: A helper library to work with threads within Flask applications.
Home-page: https://github.com/sintezcs/flask-threads.git
Author: Alexey Minakov
Author-email: a@spb.host
License-File: LICENSE
Requires-Dist: Flask>=0.9
Dynamic: author
Dynamic: author-email
Dynamic: description
Dynamic: description-content-type
Dynamic: home-page
Dynamic: license-file
Dynamic: requires-dist
Dynamic: summary
